rappiflow_providers/__init__.py
rappiflow_providers/dags/__init__.py
rappiflow_providers/dags/dag_metric_resources.py
rappiflow_providers/dags/queries/__init__.py
rappiflow_providers/operators/__init__.py
rappiflow_providers/operators/snowflake_operators.py
rappiflow_providers/operators/utils/__init__.py
rappiflow_providers/operators/utils/time_execution.py
rappiflow_providers-0.3.6.dist-info/METADATA
rappiflow_providers-0.3.6.dist-info/WHEEL
rappiflow_providers-0.3.6.dist-info/top_level.txt
rappiflow_providers-0.3.6.dist-info/RECORD
