Metadata-Version: 2.1
Name: rappiflow-providers
Version: 0.3.6
Summary: Rappiflow Dags and Operators utils
Home-page: UNKNOWN
Author: CPGS DS Team
License: UNKNOWN
Platform: UNKNOWN
Requires-Python: >=3.7
Requires-Dist: pandas (==1.2.2)
Requires-Dist: psycopg2-binary (==2.8.6)
Requires-Dist: SQLAlchemy (==1.3.23)
Requires-Dist: snowflake-sqlalchemy (==1.2.4)
